pyssandra/__init__.py
pyssandra/_pyssandra.py
pyssandra/_query_builder.py
pyssandra/py.typed
pyssandra-0.12.4.dist-info/LICENSE
pyssandra-0.12.4.dist-info/WHEEL
pyssandra-0.12.4.dist-info/METADATA
pyssandra-0.12.4.dist-info/RECORD
