Metadata-Version: 2.1
Name: pyssandra
Version: 0.12.4
Summary: Use pydantic models to create basic CQL queries.
Home-page: https://gitlab.com/mburkard/pyssandra
License: MIT
Author: Matthew Burkard
Author-email: matthewjburkard@gmail.com
Requires-Python: >=3.9,<4.0
Classifier: Intended Audience :: Developers
Classifier: License :: OSI Approved :: MIT License
Classifier: Programming Language :: Python :: 3
Classifier: Programming Language :: Python :: 3.10
Classifier: Programming Language :: Python :: 3.11
Classifier: Programming Language :: Python :: 3.9
Classifier: Topic :: Software Development
Classifier: Topic :: Software Development :: Libraries
Classifier: Topic :: Software Development :: Libraries :: Python Modules
Classifier: Typing :: Typed
Requires-Dist: case-switcher (>=1.3.13,<2.0.0)
Requires-Dist: cassandra-driver (>=3.28.0,<4.0.0)
Requires-Dist: pydantic (>=2.4.2,<3.0.0)
Project-URL: Repository, https://gitlab.com/mburkard/pyssandra
